{
  "data": [
    {
      "id": "reciuE6aswEnHJzmQ",
      "name": "ARS",
      "issuers": [
        {
          "name": "Anclap",
          "website": "https://home.anclap.com/"
        }
      ],
      "yield_bearing": false,
      "fiat_asset": "ARS",
      "home_domain": "api.anclap.com",
      "website": "https://home.anclap.com/",
      "issuer_address": "GCYE7C77EB5AWAA25R5XMWNI2EDOKTTFTTPZKM2SR5DI4B4WFD52DARS"
    },
    {
      "id": "reczAO3ddwU0mTnSu",
      "name": "ARST",
      "issuers": [
        {
          "name": "Latamex"
        }
      ],
      "yield_bearing": false,
      "fiat_asset": "ARS",
      "home_domain": "pubnet-sep.latamex.com",
      "issuer_address": "GCSAZVWXZKWS4XS223M5F54H2B6XPIIXZZGP7KEAIU6YSL5HDRGCI3DG"
    },
    {
      "id": "recufJCOwQk8vFc7k",
      "name": "AUDD",
      "issuers": [
        {
          "name": "Novatti"
        }
      ],
      "yield_bearing": false,
      "fiat_asset": "AUD",
      "home_domain": "audd.digital",
      "issuer_address": "GDC7X2MXTYSAKUUGAIQ7J7RPEIM7GXSAIWFYWWH4GLNFECQVJJLB2EEU"
    },
    {
      "id": "rec6JDIWeRUcjCDNU",
      "name": "BENJI",
      "logo": "partners/franklin-templeton.png",
      "issuer_logo": "partners/franklin-templeton.png",
      "issuers": [
        {
          "name": "Franklin Templeton",
          "logo": "partners/franklin-templeton.png"
        }
      ],
      "yield_bearing": true,
      "permissibility": "Permissioned",
      "fiat_asset": "FOBXX",
      "home_domain": "franklintempleton.com",
      "website": "franklintempleton.com",
      "issuer_address": "GBHNGLLIE3KWGKCHIKMHJ5HVZHYIK7WTBE4QF5PLAKL4CJGSEU7HZIW5"
    },
    {
      "id": "recIkmDZDxYBE3ioj",
      "name": "BRLT",
      "issuers": [
        {
          "name": "Latamex"
        }
      ],
      "yield_bearing": false,
      "fiat_asset": "BRL",
      "home_domain": "sep.stablex.cloud",
      "issuer_address": "GCHQ3F2BF5P74DMDNOOGHT5DUCKC773AW5DTOFINC26W4KGYFPYDPRSO"
    },
    {
      "id": "recg7S1GaSb0BqrJM",
      "name": "CETES",
      "issuers": [
        {
          "name": "Etherfuse"
        }
      ],
      "yield_bearing": true,
      "home_domain": "etherfuse.com",
      "website": "etherfuse.com",
      "issuer_address": "GCRYUGD5NVARGXT56XEZI5CIFCQETYHAPQQTHO2O3IQZTHDH4LATMYWC"
    },
    {
      "id": "recwGkZLYxdODYLWS",
      "name": "COP",
      "issuers": [
        {
          "name": "Anclap",
          "website": "https://home.anclap.com/"
        }
      ],
      "yield_bearing": false,
      "fiat_asset": "COP",
      "home_domain": "api2.anclap.com",
      "website": "https://home.anclap.com/",
      "issuer_address": "GC6HPU43M657FWNQVWA5DZXNOOIA7A33OF67K4SOBOF3PAO6PHALUCOP"
    },
    {
      "id": "recCfYXT2YiEoxEIY",
      "name": "EURC",
      "issuers": [
        {
          "name": "MyKobo"
        }
      ],
      "yield_bearing": false,
      "fiat_asset": "EUR",
      "home_domain": "mykobo.co",
      "issuer_address": "GAQRF3UGHBT6JYQZ7YSUYCIYWAF4T2SAA5237Q5LIQYJOHHFAWDXZ7NM"
    },
    {
      "id": "recQkS3my48RoIKkz",
      "name": "EURC",
      "logo": "partners/circle.png",
      "issuer_logo": "partners/circle.png",
      "issuers": [
        {
          "name": "Circle",
          "website": "https://www.circle.com/multi-chain-usdc/stellar",
          "logo": "partners/circle.png"
        }
      ],
      "yield_bearing": false,
      "fiat_asset": "EUR",
      "home_domain": "circle.com",
      "website": "circle.com",
      "issuer_address": "GDHU6WRG4IEQXM5NZ4BMPKOXHW76MZM4Y2IEMFDVXBSDP6SJY4ITNPP2"
    },
    {
      "id": "recEK03Xqt1HHOC2Z",
      "name": "EURT",
      "issuers": [
        {
          "name": "Tempo"
        }
      ],
      "yield_bearing": false,
      "fiat_asset": "EUR",
      "home_domain": "eurt.exchange",
      "issuer_address": "GAP5LETOV6YIE62YAM56STDANPRDO7ZFDBGSNHJQIYGGKSMOZAHOOS2S"
    },
    {
      "id": "recAcXxpP5wntgVIs",
      "name": "gBENJI",
      "logo": "partners/franklin-templeton.png",
      "issuer_logo": "partners/franklin-templeton.png",
      "issuers": [
        {
          "name": "Franklin Templeton",
          "logo": "partners/franklin-templeton.png"
        }
      ],
      "yield_bearing": true,
      "fiat_asset": "USD",
      "website": "franklintempleton.com",
      "issuer_address": "GD5J73EKK5IYL5XS3FBTHHX7CZIYRP7QXDL57XFWGC2WVYWT326OBXRP"
    },
    {
      "id": "rec4h6vVjtKNXJ4vk",
      "name": "GYEN",
      "logo": "assets/gyen.png",
      "issuers": [
        {
          "name": "GMO Trust"
        }
      ],
      "yield_bearing": false,
      "fiat_asset": "JPY",
      "home_domain": "stablecoin.z.com",
      "website": "https://stablecoin.z.com/gyen/",
      "issuer_address": "GDF6VOEGRWLOZ64PQQGKD2IYWA22RLT37GJKS2EJXZHT2VLAGWLC5TOB"
    },
    {
      "id": "recnZ88dwNPnsPZgK",
      "name": "MXNe",
      "issuers": [
        {
          "name": "Etherfuse"
        }
      ],
      "yield_bearing": false,
      "permissibility": "Permissionless",
      "fiat_asset": "MXN",
      "website": "etherfuse.com"
    },
    {
      "id": "recf1FX1JV3nMFe4H",
      "name": "NGNC",
      "issuers": [
        {
          "name": "Link"
        }
      ],
      "yield_bearing": false,
      "fiat_asset": "NGN",
      "home_domain": "ngnc.online",
      "issuer_address": "GASBV6W7GGED66MXEVC7YZHTWWYMSVYEY35USF2HJZBLABLYIFQGXZY6"
    },
    {
      "id": "recSiKI5lysrJsVEV",
      "name": "PEN",
      "issuers": [
        {
          "name": "Anclap",
          "website": "https://home.anclap.com/"
        }
      ],
      "yield_bearing": false,
      "fiat_asset": "PEN",
      "home_domain": "api.anclap.com",
      "website": "https://home.anclap.com/",
      "issuer_address": "GA4TDPNUCZPTOHB3TKUYMDCRVATXKEADH7ZEYEBWJKQKE2UBFCYNBPEN"
    },
    {
      "id": "recxdJsWIcFsu4CjI",
      "name": "PYUSD",
      "issuers": [
        {
          "name": "PayPal (PYUSD)"
        }
      ],
      "yield_bearing": false
    },
    {
      "id": "recFbiRwBYBk5EQzg",
      "name": "QCAD",
      "issuers": [
        {
          "name": "Stablecorp"
        }
      ],
      "yield_bearing": false,
      "home_domain": "stablecorp.ca",
      "issuer_address": "GBRSN6AURJN4R7RT5EDLO3SPFEZBS5FWE3W2R7RTMCYDIJH3ISSF5MKJ"
    },
    {
      "id": "recwLRmpsZGcf1tqN",
      "name": "SCOP",
      "issuers": [
        {
          "name": "StableCop"
        }
      ],
      "yield_bearing": false,
      "fiat_asset": "COL",
      "home_domain": "anchor.stablecop.com",
      "issuer_address": "GDO3PDT3IKVL2PJI5MMQDHLFYBVQI46YQW6P5TEMGOJA7LWGELWDMZNY"
    },
    {
      "id": "rectGIfFaNZeqC3ZN",
      "name": "UAH",
      "issuers": [
        {
          "name": "DCM (UAH)"
        }
      ],
      "yield_bearing": false,
      "fiat_asset": "UAH",
      "home_domain": "dcm.systems",
      "website": "dcm.systems",
      "issuer_address": "GCJI3CP2NL6NWSCHM36XBQYCBHOTVVZWEXZALWON34KAYUGF6GEVNRTS"
    },
    {
      "id": "recST8DGhgX8wjlGw",
      "name": "USDC",
      "logo": "assets/usdc.png",
      "issuer_logo": "partners/circle.png",
      "issuers": [
        {
          "name": "Circle",
          "website": "https://www.circle.com/multi-chain-usdc/stellar",
          "logo": "partners/circle.png"
        }
      ],
      "yield_bearing": false,
      "permissibility": "Permissionless",
      "fiat_asset": "USD",
      "home_domain": "centre.io",
      "website": "https://www.circle.com/usdc",
      "issuer_address": "GA5ZSEJYB37JRC5AVCIA5MOP4RHTM335X2KGX3IHOJAPP5RE34K4KZVN"
    },
    {
      "id": "reculoupeMbv6xF05",
      "name": "USDL",
      "issuers": [
        {
          "name": "Paxos"
        }
      ],
      "yield_bearing": true,
      "restricted_jurisdictions": "https://support.liftdollar.com/hc/en-us/articles/26058585903892-USDL-Restricted-Access-Jurisdictions"
    },
    {
      "id": "recOa4hyzSwhOgTKi",
      "name": "USDS",
      "issuers": [
        {
          "name": "Stably"
        }
      ],
      "yield_bearing": false,
      "fiat_asset": "USD",
      "home_domain": "polaris.stably.io",
      "issuer_address": "GBK4AYTOYIAYT4UJECSQGMACUWLKYOOM4VCAUUZ3Y3FG5XD2LYK3FGK2"
    },
    {
      "id": "rec4Isduy79y1WHal",
      "name": "USDY",
      "issuers": [
        {
          "name": "Ondo (USDY)"
        }
      ],
      "yield_bearing": true,
      "permissibility": "Permissionless",
      "restricted_jurisdictions": "To be eligible to acquire, redeem, or trade USDY, you (or your organization, depending upon who is investing) must NOT be located, organized, or a resident in any of the following locations: The United States (including its possessions and territories), United Kingdom or Canada."
    },
    {
      "id": "recg499ceex97oJar",
      "name": "USTRY",
      "issuers": [
        {
          "name": "Etherfuse"
        }
      ],
      "yield_bearing": true,
      "home_domain": "etherfuse.com",
      "website": "etherfuse.com",
      "issuer_address": "GCRYUGD5NVARGXT56XEZI5CIFCQETYHAPQQTHO2O3IQZTHDH4LATMYWC"
    },
    {
      "id": "recLEYlI0zyraB1bi",
      "name": "VCHF",
      "issuers": [
        {
          "name": "VNX"
        }
      ],
      "yield_bearing": false,
      "fiat_asset": "CHF",
      "home_domain": "vnx.li",
      "issuer_address": "GDXLSLCOPPHTWOQXLLKSVN4VN3G67WD2ENU7UMVAROEYVJLSPSEWXIZN"
    },
    {
      "id": "reciCMb6Aa2q5vTGq",
      "name": "VEUR",
      "issuers": [
        {
          "name": "VNX"
        }
      ],
      "yield_bearing": false,
      "fiat_asset": "EUR",
      "home_domain": "vnx.li",
      "issuer_address": "GDXLSLCOPPHTWOQXLLKSVN4VN3G67WD2ENU7UMVAROEYVJLSPSEWXIZN"
    },
    {
      "id": "rec9ZGmOFaYrMq2SE",
      "name": "ZUSD",
      "logo": "assets/zusd.png",
      "issuers": [
        {
          "name": "GMO Trust"
        }
      ],
      "yield_bearing": false,
      "fiat_asset": "USD",
      "home_domain": "stablecoin.z.com",
      "website": "https://stablecoin.z.com/zusd/",
      "issuer_address": "GDF6VOEGRWLOZ64PQQGKD2IYWA22RLT37GJKS2EJXZHT2VLAGWLC5TOB"
    }
  ],
  "metadata": {
    "generatedAt": "2025-08-05T22:45:54.912Z",
    "count": 27,
    "source": "airtable"
  }
}